xhs_mcp/__init__.py
xhs_mcp/__main__.py
xhs_mcp/api/xhs_api.py
xhs_mcp/api/xhsvm.js
iflow_mcp_xhs_mcp-0.1.1.dist-info/METADATA
iflow_mcp_xhs_mcp-0.1.1.dist-info/WHEEL
iflow_mcp_xhs_mcp-0.1.1.dist-info/entry_points.txt
iflow_mcp_xhs_mcp-0.1.1.dist-info/RECORD
