Metadata-Version: 2.4
Name: iflow-mcp_xhs-mcp
Version: 0.1.1
Summary: 小红书MCP服务器 - 提供小红书API功能的MCP工具
Project-URL: Homepage, https://github.com/jobsonlook/xhs-mcp
Project-URL: Repository, https://github.com/jobsonlook/xhs-mcp
Author-email: Your Name <your.email@example.com>
License: MIT
Keywords: api,mcp,server,xiaohongshu
Classifier: Development Status :: 3 - Alpha
Classifier: Intended Audience :: Developers
Classifier: License :: OSI Approved :: MIT License
Classifier: Programming Language :: Python :: 3
Classifier: Programming Language :: Python :: 3.12
Requires-Python: >=3.12
Requires-Dist: curl-cffi>=0.10.0
Requires-Dist: mcp[cli]>=1.6.0
Requires-Dist: pyexecjs>=1.5.1
Requires-Dist: requests>=2.32.3
